chemprep/__init__.py
chemprep/cli.py
chemprep/descriptors.py
chemprep/fingerprints.py
chemprep/similarity.py
chemprep-0.1.0.dist-info/METADATA
chemprep-0.1.0.dist-info/WHEEL
chemprep-0.1.0.dist-info/entry_points.txt
chemprep-0.1.0.dist-info/licenses/LICENSE
chemprep-0.1.0.dist-info/RECORD
