Metadata-Version: 2.4
Name: chemprep
Version: 0.1.0
Summary: A Python library for molecular fingerprinting and similarity calculations.
Project-URL: Homepage, https://github.com/santuchal/ChemPrep
Author-email: "Santu Chall and Dr. Sourav Roy" <santuchal@gmail.com>
License-File: LICENSE
Classifier: License :: OSI Approved :: MIT License
Classifier: Operating System :: OS Independent
Classifier: Programming Language :: Python :: 3
Requires-Python: >=3.7
Requires-Dist: pandas
Requires-Dist: rdkit==2025.3.3
